mypromptgen/__init__.py
mypromptgen/distill.py
mypromptgen/main.py
mypromptgen/migrate.py
mypromptgen/qlora.py
mypromptgen-0.3.1.dist-info/licenses/LICENSE
mypromptgen-0.3.1.dist-info/METADATA
mypromptgen-0.3.1.dist-info/WHEEL
mypromptgen-0.3.1.dist-info/entry_points.txt
mypromptgen-0.3.1.dist-info/top_level.txt
mypromptgen-0.3.1.dist-info/RECORD
